ironcageai/__init__.py
ironcageai-0.1.0.dist-info/licenses/license
ironcageai-0.1.0.dist-info/METADATA
ironcageai-0.1.0.dist-info/WHEEL
ironcageai-0.1.0.dist-info/top_level.txt
ironcageai-0.1.0.dist-info/RECORD
